{"core_helper.md":"r2NXQXPd","server_advance_custom.md":"CMb90I8m","server_standard.md":"BlaXtEUL","server_advance_parallel-route.md":"BZoL8W22","server_advance_phecda-core.md":"dhAu56dD","server_advance_module.md":"46lq49do","server_aop_filter.md":"DPlXIDND","server_other_compare.md":"CfAMjGED","server_other_problem.md":"B8wKygEr","server_aop_plugin.md":"DUeDRbQd","server_aop_guard.md":"DjeI2lWP","server_aop_pipe.md":"CevxiARW","vue_phecda-core.md":"CNmoIwXl","core_core.md":"Dpc1YOJl","server_other_inspire.md":"CPzCBWCa","server_advance_bun-or-deno.md":"Cm6fKuVu","core_decorator.md":"BOF5_XAX","server_other_types.md":"BKnC2oVU","server_advance_bundle.md":"BH5P0u6G","vue_base.md":"CaOhNxkq","vue_module.md":"Kwvlyelh","server_intro.md":"HJW-YIAG","index.md":"CbMKQqNC","server_advance_rpc.md":"CdsumlZ3","core_intro.md":"29qOCa7l","server_aop_interceptor.md":"BR15xtG0","server_advance_cross-project.md":"BS4BRTG7","server_base.md":"B6waxV3g","core_standard.md":"CUR7G1xQ","server_quick-start.md":"BQfb-kJ6","server_advance_limit.md":"0qd5W-Nu","server_other_changelog.md":"BDyrVyeT","core_validate.md":"BKS0tTPk","server_aop_extension.md":"Y_XmkqMS","server_advance_hmr.md":"Bdjdr2aX","server_advance_command.md":"DM61_T-s"}
