{"core_decorator.md":"BGcXNjnw","core_intro.md":"Cxij-ZhV","core_utils.md":"DAgAuqKx","core_validate.md":"D6OPD_wT","index.md":"DbxmPI-V","server_advance_custom.md":"BqiFCRkF","server_advance_hmr.md":"rW3449gA","server_advance_multi-extend.md":"BW4Fylpr","server_advance_openapi.md":"BU8iNPr_","server_advance_outside-module.md":"D_oM8TOz","server_advance_parallel-route.md":"DAvSesQT","server_advance_test.md":"RizVk5CV","server_aop_addon.md":"CzvyjunP","server_aop_ctx.md":"DLPxBW6d","server_aop_define.md":"Dwkw-lW6","server_aop_extension.md":"DS54e3TA","server_aop_filter.md":"BeY-qII1","server_aop_guard.md":"DJ5_RZ1k","server_aop_pipe.md":"ATkt5AXt","server_base.md":"Dr9xlRnQ","server_build_bundle.md":"DbGsXGfp","server_build_cross-project.md":"gtluetpM","server_build_module-as-lib.md":"CqgRHRmc","server_feature_dep-inject.md":"CPnnLLvw","server_feature_file-upload.md":"D-nJMRQ9","server_feature_internal-module.md":"BtGzG6Dc","server_feature_log.md":"CJHA1yGc","server_feature_phecda-core.md":"BDReOF4N","server_inspire.md":"eLPEWlCg","server_intro.md":"CpYLYoJ2","server_must-know_limit.md":"DYnuKv92","server_must-know_problem.md":"DU4VcS5v","server_other_bun-or-deno.md":"W-YooR9q","server_other_types.md":"gUwdLK1z","server_quick-start.md":"Wd2ZiwI5","server_rpc_rpc.md":"Ct9GOnUi","server_rpc_ws_electron.md":"CzFLmfA1","server_runtime_command.md":"DSVXPExa","server_runtime_environment.md":"Dl_N_lED","server_runtime_unimport.md":"oqa958T0","server_standard.md":"DvBX8vyZ","web_api.md":"CBzpPpud","web_base.md":"84w_QaOG","web_intro.md":"DGM2cnYz","web_react_base.md":"BawplbOi","web_vue_base.md":"ChkOTUss"}
